types_paddle/__init__.py
types_paddle/cli.py
types_paddle/tensor.py
types_paddle/tensor.pyi
types_paddle-0.0.2.dist-info/LICENSE
types_paddle-0.0.2.dist-info/METADATA
types_paddle-0.0.2.dist-info/WHEEL
types_paddle-0.0.2.dist-info/entry_points.txt
types_paddle-0.0.2.dist-info/top_level.txt
types_paddle-0.0.2.dist-info/RECORD
