Metadata-Version: 2.1
Name: types-paddle
Version: 0.0.2
Summary: type stub files for paddle to make tensor more intelligence in IDE
Home-page: https://github.com/wj-Mcat/types-paddle
Author: Jingjing WU (吴京京)
Author-email: wujingjing05@baidu.com
License: Apache-2.0
Classifier: Programming Language :: Python :: 3.7
Classifier: License :: OSI Approved :: Apache Software License
Classifier: Operating System :: OS Independent
License-File: LICENSE
